knot_floer_homology/__init__.py
knot_floer_homology/test.py
knot_floer_homology/hfk.cpython-39-aarch64-linux-gnu.so
knot_floer_homology/HFK_data.json
knot_floer_homology-1.2.2.dist-info/RECORD
knot_floer_homology-1.2.2.dist-info/top_level.txt
knot_floer_homology-1.2.2.dist-info/WHEEL
knot_floer_homology-1.2.2.dist-info/METADATA
