Metadata-Version: 2.1
Name: knot_floer_homology
Version: 1.2.2
Summary: Python wrapper for Zoltán Szabó's HFK Calculator
Author: Zoltán Szabó, Marc Culler, Nathan M. Dunfield, Matthias Goerner
Author-email: snappy-help@computop.org
Project-URL: Homepage, https://github.com/3-manifolds/knot_floer_homology
Classifier: Development Status :: 5 - Production/Stable
Classifier: License :: OSI Approved :: GNU General Public License v2 or later (GPLv2+)
Classifier: Programming Language :: C++
Classifier: Operating System :: OS Independent
Requires-Python: >=3.8
